ipymap/__init__.py
ipymap/map.py
ipymap-0.0.4.dist-info/METADATA
ipymap-0.0.4.dist-info/RECORD
ipymap-0.0.4.dist-info/WHEEL
ipymap-0.0.4.dist-info/top_level.txt
